blocknative/__init__.py
blocknative/exceptions.py
blocknative/stream.py
blocknative/utils.py
blocknative_sdk-0.2.9.dist-info/METADATA
blocknative_sdk-0.2.9.dist-info/WHEEL
blocknative_sdk-0.2.9.dist-info/top_level.txt
blocknative_sdk-0.2.9.dist-info/RECORD
