Metadata-Version: 2.1
Name: blocknative-sdk
Version: 0.2.9
Summary: Blocknative's Python SDK.
Home-page: https://github.com/blocknative/python-sdk
Author: Taylor Dawson
Author-email: taylor@blocknative.com
Keywords: ethereum,api,transactions,blocknative
Requires-Python: >=3.7
Requires-Dist: async-generator (==1.10)
Requires-Dist: attrs (==21.2.0)
Requires-Dist: h11 (==0.12.0)
Requires-Dist: idna (==3.2)
Requires-Dist: outcome (==1.1.0)
Requires-Dist: sniffio (==1.2.0)
Requires-Dist: sortedcontainers (==2.4.0)
Requires-Dist: trio (==0.19.0)
Requires-Dist: trio-websocket (==0.9.2)
Requires-Dist: wsproto (==1.0.0)
Requires-Dist: myst-parser (==0.18.0)
Requires-Dist: sphinx-rtd-theme (==1.0.0)
Requires-Dist: sphinx (==5.0.2)
